python_docker_test-0.1.0.dist-info/DESCRIPTION.rst
python_docker_test-0.1.0.dist-info/zip-safe
python_docker_test-0.1.0.dist-info/top_level.txt
python_docker_test-0.1.0.dist-info/metadata.json
python_docker_test-0.1.0.dist-info/WHEEL
python_docker_test-0.1.0.dist-info/RECORD
python_docker_test-0.1.0.dist-info/METADATA
python_docker_test/__init__.py
python_docker_test/mixin.py
