Metadata-Version: 2.0
Name: python-docker-test
Version: 0.1.0
Summary: A unittest.TestCase mixin for executing integration/acceptance tests against containerized services
Home-page: https://github.com/harvard-dce/python-docker-test
Author: Jay Luker
Author-email: jay_luker@harvard.edu
License: MIT License
Keywords: docker integration acceptance testing
Platform: UNKNOWN
Requires-Dist: docker-py
Requires-Dist: requests
